mannequin/__init__.py
mannequin-0.0.1.dist-info/WHEEL
mannequin-0.0.1.dist-info/METADATA
mannequin-0.0.1.dist-info/RECORD
